embedselection-1.0.dist-info/licenses/LICENSE
run/__init__.py
run/run.py
embedselection-1.0.dist-info/METADATA
embedselection-1.0.dist-info/WHEEL
embedselection-1.0.dist-info/entry_points.txt
embedselection-1.0.dist-info/top_level.txt
embedselection-1.0.dist-info/RECORD
