Metadata-Version: 2.4
Name: EmbedSelection
Version: 1.0
Summary: Embedding selection: A tool for selecting the best embedding model for your use case
Home-page: https://github.com/AmadeusITGroup/EmbSelection
Author: Ilias, Hongliu
Author-email: ilias.driouich@amadeus.com;hongliu.cao@amadeus.com
Requires-Python: >=3.6
License-File: LICENSE
Requires-Dist: pandas>=1.1.0
Requires-Dist: numpy>=1.19.0
Dynamic: author
Dynamic: author-email
Dynamic: description
Dynamic: description-content-type
Dynamic: home-page
Dynamic: license-file
Dynamic: requires-dist
Dynamic: requires-python
Dynamic: summary
